os_dbnetget/VERSION
os_dbnetget/__init__.py
os_dbnetget/cmdline.py
os_dbnetget/exceptions.py
os_dbnetget/utils.py
os_dbnetget/clients/__init__.py
os_dbnetget/clients/client.py
os_dbnetget/clients/sync_client.py
os_dbnetget/clients/tornado_client.py
os_dbnetget/commands/__init__.py
os_dbnetget/commands/qdb/__init__.py
os_dbnetget/commands/qdb/default_runner.py
os_dbnetget/commands/qdb/m3_runner.py
os_dbnetget/commands/qdb/processor.py
os_dbnetget/commands/qdb/tornado_runner.py
os_dbnetget/commands/qdb/get/__init__.py
os_dbnetget/commands/qdb/get/default_get.py
os_dbnetget/commands/qdb/get/m3_get.py
os_dbnetget/commands/qdb/get/processor.py
os_dbnetget/commands/qdb/get/tornado_get.py
os_dbnetget/commands/qdb/test/__init__.py
os_dbnetget/commands/qdb/test/default_test.py
os_dbnetget/commands/qdb/test/m3_test.py
os_dbnetget/commands/qdb/test/processor.py
os_dbnetget/commands/qdb/test/tornado_test.py
python_os_dbnetget-0.1.4.dist-info/LICENSE
python_os_dbnetget-0.1.4.dist-info/METADATA
python_os_dbnetget-0.1.4.dist-info/WHEEL
python_os_dbnetget-0.1.4.dist-info/entry_points.txt
python_os_dbnetget-0.1.4.dist-info/top_level.txt
python_os_dbnetget-0.1.4.dist-info/RECORD
